LICENSE.txt
MANIFEST.in
README.md
setup.py
docs/README.rst
jsongrep/__init__.py
jsongrep/base.py
jsongrep/matchers.py
jsongrep.egg-info/PKG-INFO
jsongrep.egg-info/SOURCES.txt
jsongrep.egg-info/dependency_links.txt
jsongrep.egg-info/entry_points.txt
jsongrep.egg-info/requires.txt
jsongrep.egg-info/top_level.txt
jsongrep.egg-info/zip-safe
jsongrep/glob/__init__.py
jsongrep/glob/matchers.py
jsongrep/glob/syntax.py
jsongrep/regexp/__init__.py
jsongrep/regexp/matchers.py
jsongrep/regexp/syntax.py
tests/ongz.json