Metadata-Version: 1.0
Name: jsongrep
Version: 0.1.1
Summary: Search and select bits out of a JSON document.
Home-page: http://tire.less.ly/hacking/jsongrep
Author: David Schoonover
Author-email: dsc@less.ly
License: MIT
Download-URL: http://pypi.python.org/packages/source/j/jsongrep/jsongrep-0.1.1.tar.gz
Keywords: jsongrep,json,grep,search,console,cli,shell
Platform: UNKNOWN
Classifier: Programming Language :: Python
Classifier: Development Status :: 5 - Production/Stable
Classifier: License :: OSI Approved :: MIT License
Classifier: Operating System :: OS Independent
Classifier: Intended Audience :: Developers
Classifier: Topic :: Software Development
Classifier: Topic :: Software Development :: Libraries
Classifier: Topic :: Utilities
